MANIFEST.in
setup.py
anthill/message/__init__.py
anthill/message/admin.py
anthill/message/handler.py
anthill/message/options.py
anthill/message/server.py
anthill/message/model/__init__.py
anthill/message/model/conversation.py
anthill/message/model/group.py
anthill/message/model/history.py
anthill/message/model/online.py
anthill/message/model/queue.py
anthill/message/sql/group_cluster_accounts.sql
anthill/message/sql/group_clusters.sql
anthill/message/sql/group_participants.sql
anthill/message/sql/groups.sql
anthill/message/sql/last_read_message.sql
anthill/message/sql/messages.sql
anthill/message/static/admin/messages.js
anthill_message.egg-info/PKG-INFO
anthill_message.egg-info/SOURCES.txt
anthill_message.egg-info/dependency_links.txt
anthill_message.egg-info/namespace_packages.txt
anthill_message.egg-info/not-zip-safe
anthill_message.egg-info/requires.txt
anthill_message.egg-info/top_level.txt