Metadata-Version: 1.0
Name: anthill-message
Version: 0.2
Summary: A messaging service for Anthill platform
Home-page: https://github.com/anthill-platform/anthill-message
Author: desertkun
Author-email: desertkun@gmail.com
License: MIT
Platform: UNKNOWN
